README.rst
setup.py
musicLegacy/__init__.py
musicLegacy/converters.py
musicLegacy/effects.py
musicLegacy/synths.py
musicLegacy/tables.py
musicLegacy/utils.py
musicLegacy.egg-info/PKG-INFO
musicLegacy.egg-info/SOURCES.txt
musicLegacy.egg-info/dependency_links.txt
musicLegacy.egg-info/requires.txt
musicLegacy.egg-info/top_level.txt
musicLegacy/pieces/__init__.py
musicLegacy/pieces/fourHubsDance.py