Metadata-Version: 1.1
Name: musicLegacy
Version: 0.1.dev13
Summary: Yet another music package using the MASS (Music and Audio in Sample Sequences) framework
Home-page: https://github.com/ttm/musicLegacy
Author: Renato Fabbri
Author-email: renato.fabbri@gmail.com
License: MIT
Keywords: music audio dsp psychophysics physics synthesis toolbox
Platform: UNKNOWN
Classifier: Development Status :: 2 - Pre-Alpha
Classifier: Intended Audience :: Science/Research
Classifier: Intended Audience :: Developers
Classifier: Intended Audience :: Telecommunications Industry
Classifier: Intended Audience :: Education
Classifier: Intended Audience :: Religion
Classifier: Intended Audience :: Other Audience
Classifier: Topic :: Scientific/Engineering :: Physics
Classifier: Topic :: Scientific/Engineering :: Visualization
Classifier: Topic :: Scientific/Engineering :: Information Analysis
Classifier: Topic :: Multimedia :: Sound/Audio :: Sound Synthesis
Classifier: Topic :: Multimedia :: Sound/Audio :: Analysis
Classifier: Topic :: Multimedia :: Sound/Audio :: Editors
Classifier: Topic :: Multimedia :: Sound/Audio :: Mixers
Classifier: Topic :: Multimedia :: Sound/Audio :: Speech
Classifier: Topic :: Artistic Software
Classifier: Topic :: Other/Nonlisted Topic
Classifier: License :: OSI Approved :: MIT License
Classifier: Programming Language :: Python :: 3
